ckipnlp/__init__.py
ckipnlp/container/__init__.py
ckipnlp/container/base.py
ckipnlp/container/coref.py
ckipnlp/container/ner.py
ckipnlp/container/parse.py
ckipnlp/container/seg.py
ckipnlp/container/text.py
ckipnlp/container/util/__init__.py
ckipnlp/container/util/parse_tree.py
ckipnlp/container/util/wspos.py
ckipnlp/data/conparse.py
ckipnlp/data/coref/__init__.py
ckipnlp/data/coref/_pronoun.py
ckipnlp/data/coref/_self.py
ckipnlp/data/coref/_human/__init__.py
ckipnlp/data/coref/_human/_alumnus.py
ckipnlp/data/coref/_human/_aristocrat.py
ckipnlp/data/coref/_human/_candidate.py
ckipnlp/data/coref/_human/_fans.py
ckipnlp/data/coref/_human/_humanized.py
ckipnlp/data/coref/_human/_instance.py
ckipnlp/data/coref/_human/_member.py
ckipnlp/data/coref/_human/_owner.py
ckipnlp/data/coref/_human/_professional.py
ckipnlp/data/coref/_human/_recipient.py
ckipnlp/data/coref/_human/_religious_follower.py
ckipnlp/data/coref/_human/_sage.py
ckipnlp/data/coref/_human/_sick_patient.py
ckipnlp/data/coref/_human/_student.py
ckipnlp/data/coref/_human/_talent.py
ckipnlp/data/coref/_human/_victim.py
ckipnlp/data/coref/_human/_warrior.py
ckipnlp/driver/__init__.py
ckipnlp/driver/base.py
ckipnlp/driver/classic.py
ckipnlp/driver/coref.py
ckipnlp/driver/ss.py
ckipnlp/driver/tagger.py
ckipnlp/pipeline/__init__.py
ckipnlp/pipeline/coref.py
ckipnlp/pipeline/kernel.py
ckipnlp/util/__init__.py
ckipnlp/util/data.py
ckipnlp/util/logger.py
ckipnlp-1.0.3.dist-info/LICENSE
ckipnlp-1.0.3.dist-info/METADATA
ckipnlp-1.0.3.dist-info/WHEEL
ckipnlp-1.0.3.dist-info/top_level.txt
ckipnlp-1.0.3.dist-info/RECORD
