Metadata-Version: 2.1
Name: ckipnlp
Version: 1.0.3
Summary: CKIP CoreNLP
Home-page: https://ckipnlp.readthedocs.io
Download-URL: https://ckipnlp.readthedocs.io/tarball/1.0.3
Author: Mu Yang
Author-email: emfomy@gmail.com
License: GPL-3.0
Platform: linux_x86_64
Classifier: Development Status :: 5 - Production/Stable
Classifier: Environment :: Console
Classifier: Programming Language :: Python
Classifier: Programming Language :: Python :: 3
Classifier: Programming Language :: Python :: 3.6
Classifier: Programming Language :: Python :: 3.7
Classifier: Programming Language :: Python :: 3.8
Classifier: Programming Language :: Python :: 3 :: Only
Classifier: License :: OSI Approved :: GNU General Public License v3 (GPLv3)
Classifier: Operating System :: POSIX :: Linux
Classifier: Natural Language :: Chinese (Traditional)
Requires-Python: >=3.6
License-File: LICENSE
Requires-Dist: appdirs (>=1.4.3)
Requires-Dist: numpy (>=1.18)
Requires-Dist: treelib (>=1.5.5)
Provides-Extra: classic
Requires-Dist: ckip-classic (>=1.1.2) ; extra == 'classic'
Provides-Extra: tagger
Requires-Dist: ckiptagger[tf] (>=0.2.1) ; extra == 'tagger'
Provides-Extra: tagger-gpu
Requires-Dist: ckiptagger[tfgpu] (>=0.2.1) ; extra == 'tagger-gpu'
